{"city":{"id":"13224","name":"多摩市","prefecture":"東京都","rank":"C","dataVersion":"2026-05","rules":{"definition":"家庭から出る大型ごみのことで、有料指定袋に入らないものや、重さが5キログラム以上のもの","contact":"042-375-9713（粗大ごみ専用ダイヤル）","hours":"月〜金 8:30〜17:00（祝日・年末年始除く）","internetHours":"電子申請24時間365日受付","websiteUrl":"https://www.city.tama.lg.jp/kurashi/gomi/sodai/index.html","applicationMethod":"電話（042-375-9713）/ 電子申請（スマホ・PC）/ FAX（042-356-3919）。収集日の2週間前から前日15時まで（前日が祝日の場合は直前の平日15時まで）受付","paymentMethod":"粗大ごみ処理券（200円券・400円券の2種類）を取扱店で購入し組み合わせる。例：800円の場合は200円券2枚＋400円券1枚。電子申請の場合はクレジットカードまたはPayPay決済可","collectionMethod":"収集日前日夜から当日朝8:00までに指定場所へ。処理券に氏名または受付番号を記入して貼付。1回3点まで（引越時最終週のみ6点まで）","selfCarryIn":"多摩ニュータウン環境組合 多摩清掃工場へ持込可。事前に粗大ごみ専用ダイヤル（042-375-9713）で要申込。市内在住者本人のみ・運転免許証等で住所確認。平日8:30〜11:30・13:00〜16:30、毎月第4日曜日同時間帯。10kgあたり250円・現金払いのみ（処理券利用不可）。10kg未満は10kgとして計算","feeRevisionNote":"処理券は200円券・400円券の2種類。600円以上の品目は複数枚組み合わせて準備。剪定枝・落ち葉・刈草は無料。料金表に記載のない品目は3辺の和と重量による7段階（200円・400円・600円・800円・1,200円・1,600円・2,400円）で決定","nonCollectibleNote":"家電リサイクル4品目（エアコン・テレビ・冷蔵庫・冷凍庫・洗濯機）、パソコン、原付バイク・オートバイ、消火器、タイヤ、バッテリー等は収集・持込不可"}},"items":[
{"n":"アコーディオンカーテン","k":["あ"],"fee":400,"m":"収集／持込可","tags":["カーテン","仕切り","間仕切り"],"en":"Accordion Curtain"},
{"n":"編み機","k":["あ"],"fee":400,"m":"収集／持込可","tags":["手芸","ニット","編物"],"en":"Knitting Machine"},
{"n":"アシスト付自転車（バッテリー除く）","k":["あ"],"fee":800,"m":"収集／持込可","tags":["電動アシスト","自転車","チャリ"],"en":"Electric Assist Bicycle (without battery)"},
{"n":"アイロン台","k":["あ"],"fee":200,"m":"収集／持込可","tags":["アイロン","折り畳み","裁縫"],"en":"Ironing Board"},
{"n":"アンテナ（屋内・屋外）","k":["あ"],"fee":200,"m":"収集／持込可","tags":["テレビ","受信","屋根"],"en":"Antenna"},
{"n":"アンプ（家庭用）","k":["あ"],"fee":200,"m":"収集／持込可","tags":["音響","オーディオ","スピーカー"],"en":"Amplifier (home use)"},
{"n":"いす（1人掛け）","k":["あ"],"fee":200,"m":"収集／持込可","tags":["椅子","チェア","座いす"],"en":"Chair (1 seat)"},
{"n":"いす（2人掛け以上）","k":["あ"],"fee":400,"m":"収集／持込可","tags":["椅子","ベンチ","2人"],"en":"Chair (2+ seats)"},
{"n":"一輪車","k":["あ"],"fee":200,"m":"収集／持込可","tags":["子供用","乗物","運搬"],"en":"Unicycle / Wheelbarrow"},
{"n":"衣装箱","k":["あ"],"fee":200,"m":"収集／持込可","tags":["収納","ケース","衣類"],"en":"Clothing Storage Box"},
{"n":"イーゼル","k":["あ"],"fee":200,"m":"収集／持込可","tags":["画材","絵画","三脚"],"en":"Easel"},
{"n":"インラインスケート","k":["あ"],"fee":200,"m":"収集／持込可","tags":["ローラー","スポーツ","靴"],"en":"Inline Skates"},
{"n":"ウォシュレット","k":["あ"],"fee":200,"m":"収集／持込可","tags":["温水洗浄便座","トイレ","便座"],"en":"Bidet Toilet Seat"},
{"n":"ウクレレ","k":["あ"],"fee":200,"m":"収集／持込可","tags":["楽器","ハワイ","弦楽器"],"en":"Ukulele"},
{"n":"植木鉢（陶器・大型）","k":["あ"],"fee":200,"m":"収集／持込可","tags":["園芸","鉢","ガーデニング"],"en":"Flower Pot (large)"},
{"n":"ウォーターサーバー","k":["あ"],"fee":600,"m":"収集／持込可","tags":["給水","家電","水"],"en":"Water Server"},
{"n":"絵画額（大型）","k":["あ"],"fee":200,"m":"収集／持込可","tags":["額縁","絵","アート"],"en":"Picture Frame (large)"},
{"n":"応接用いす（1人掛け）","k":["あ"],"fee":400,"m":"収集／持込可","tags":["ソファ","応接","椅子"],"en":"Reception Chair (1 seat)"},
{"n":"応接用いす（2人掛け以上）","k":["あ"],"fee":800,"m":"収集／持込可","tags":["ソファ","応接","2人掛け"],"en":"Reception Chair (2+ seats)"},
{"n":"応接テーブル","k":["あ"],"fee":600,"m":"収集／持込可","tags":["テーブル","応接","リビング"],"en":"Reception Table"},
{"n":"オーディオラック","k":["あ"],"fee":400,"m":"収集／持込可","tags":["AV","収納","ラック"],"en":"Audio Rack"},
{"n":"オーブントースター","k":["あ"],"fee":200,"m":"収集／持込可","tags":["トースター","調理","家電"],"en":"Oven Toaster"},
{"n":"折り畳みテーブル","k":["あ"],"fee":400,"m":"収集／持込可","tags":["折畳","机","テーブル"],"en":"Folding Table"},
{"n":"折り畳みベッド","k":["あ"],"fee":800,"m":"収集／持込可","tags":["折畳","ベッド","簡易"],"en":"Folding Bed"},
{"n":"折り畳みいす","k":["あ"],"fee":200,"m":"収集／持込可","tags":["折畳","椅子","パイプ"],"en":"Folding Chair"},
{"n":"オルガン","k":["あ"],"fee":1200,"m":"収集／持込可","tags":["楽器","鍵盤","電子"],"en":"Organ"},
{"n":"カーペット（4畳半まで）","k":["か"],"fee":200,"m":"収集／持込可","tags":["敷物","ラグ","カーペット"],"en":"Carpet (under 4.5 tatami)"},
{"n":"カーペット（4畳半超）","k":["か"],"fee":400,"m":"収集／持込可","tags":["敷物","ラグ","大型カーペット"],"en":"Carpet (over 4.5 tatami)"},
{"n":"カーテンレール","k":["か"],"fee":200,"m":"収集／持込可","tags":["カーテン","レール","窓"],"en":"Curtain Rail"},
{"n":"鏡台（ドレッサー）","k":["か"],"fee":800,"m":"収集／持込可","tags":["化粧台","ミラー","ドレッサー"],"en":"Vanity / Dressing Table"},
{"n":"傘立て","k":["か"],"fee":200,"m":"収集／持込可","tags":["かさたて","玄関","傘"],"en":"Umbrella Stand"},
{"n":"カセットコンロ","k":["か"],"fee":200,"m":"収集／持込可","tags":["卓上","ガス","アウトドア"],"en":"Portable Gas Stove"},
{"n":"カセットデッキ","k":["か"],"fee":200,"m":"収集／持込可","tags":["音響","テープ","オーディオ"],"en":"Cassette Deck"},
{"n":"カラーボックス（高さ90cm迄）","k":["か"],"fee":200,"m":"収集／持込可","tags":["収納","本棚","ラック"],"en":"Color Box (under 90cm)"},
{"n":"カラーボックス（高さ90cm超）","k":["か"],"fee":400,"m":"収集／持込可","tags":["収納","本棚","大型"],"en":"Color Box (over 90cm)"},
{"n":"カラオケ機器（家庭用）","k":["か"],"fee":400,"m":"収集／持込可","tags":["カラオケ","音響","マイク"],"en":"Karaoke Machine (home use)"},
{"n":"ガステーブル（1口コンロ除く）","k":["か"],"fee":400,"m":"収集／持込可","tags":["ガスコンロ","コンロ","台所"],"en":"Gas Stove / Gas Range"},
{"n":"ガスファンヒーター","k":["か"],"fee":400,"m":"収集／持込可","tags":["暖房","ガス","ファン"],"en":"Gas Fan Heater"},
{"n":"ガラスケース","k":["か"],"fee":400,"m":"収集／持込可","tags":["コレクション","展示","収納"],"en":"Glass Case"},
{"n":"ガーデニングテーブル","k":["か"],"fee":400,"m":"収集／持込可","tags":["庭","アウトドア","テーブル"],"en":"Garden Table"},
{"n":"ガーデニング椅子","k":["か"],"fee":200,"m":"収集／持込可","tags":["庭","アウトドア","椅子"],"en":"Garden Chair"},
{"n":"換気扇","k":["か"],"fee":200,"m":"収集／持込可","tags":["台所","ファン","設備"],"en":"Ventilation Fan"},
{"n":"観葉植物用プランター（大型）","k":["か"],"fee":200,"m":"収集／持込可","tags":["園芸","鉢","プランター"],"en":"Large Planter"},
{"n":"乾燥機（衣類用・家庭用）","k":["か"],"fee":1600,"m":"収集／持込可","tags":["衣類乾燥","家電","乾燥"],"en":"Clothes Dryer"},
{"n":"ギター","k":["か"],"fee":200,"m":"収集／持込可","tags":["楽器","エレキ","アコギ"],"en":"Guitar"},
{"n":"キーボード（電子楽器）","k":["か"],"fee":400,"m":"収集／持込可","tags":["楽器","鍵盤","電子"],"en":"Keyboard (musical instrument)"},
{"n":"キャビネット（小型）","k":["か"],"fee":400,"m":"収集／持込可","tags":["収納","戸棚","リビング"],"en":"Cabinet (small)"},
{"n":"キャビネット（中型）","k":["か"],"fee":600,"m":"収集／持込可","tags":["収納","戸棚","大型"],"en":"Cabinet (medium)"},
{"n":"キャリーカート","k":["か"],"fee":200,"m":"収集／持込可","tags":["買物","運搬","折畳"],"en":"Carry Cart"},
{"n":"キャンプ用テーブル","k":["か"],"fee":400,"m":"収集／持込可","tags":["アウトドア","折り畳み","テーブル"],"en":"Camping Table"},
{"n":"キャンプ用テント","k":["か"],"fee":400,"m":"収集／持込可","tags":["アウトドア","テント","キャンプ"],"en":"Camping Tent"},
{"n":"キャンピングチェア","k":["か"],"fee":200,"m":"収集／持込可","tags":["アウトドア","椅子","キャンプ"],"en":"Camping Chair"},
{"n":"金庫（手提げ・小型）","k":["か"],"fee":400,"m":"収集／持込可","tags":["セキュリティ","小型","金庫"],"en":"Safe (small / handheld)"},
{"n":"クーラーボックス","k":["か"],"fee":200,"m":"収集／持込可","tags":["保冷","アウトドア","クーラー"],"en":"Cooler Box"},
{"n":"空気清浄機","k":["か"],"fee":200,"m":"収集／持込可","tags":["クリーナー","花粉","空気"],"en":"Air Purifier"},
{"n":"クッション（特大）","k":["か"],"fee":200,"m":"収集／持込可","tags":["寝具","座","ビーズ"],"en":"Cushion (extra large)"},
{"n":"靴箱（下駄箱・小型）","k":["か"],"fee":400,"m":"収集／持込可","tags":["玄関","収納","下駄箱"],"en":"Shoe Cabinet (small)"},
{"n":"靴箱（下駄箱・大型）","k":["か"],"fee":600,"m":"収集／持込可","tags":["玄関","収納","大型"],"en":"Shoe Cabinet (large)"},
{"n":"こたつ板","k":["か"],"fee":200,"m":"収集／持込可","tags":["天板","和家具","炬燵"],"en":"Kotatsu Top Board"},
{"n":"こたつやぐら（本体）","k":["か"],"fee":200,"m":"収集／持込可","tags":["炬燵","本体","和家具"],"en":"Kotatsu Frame"},
{"n":"健康器具（電動型）","k":["か"],"fee":1200,"m":"収集／持込可","tags":["フィットネス","運動","電動"],"en":"Health Equipment (electric)"},
{"n":"健康器具（非電動型）","k":["か"],"fee":600,"m":"収集／持込可","tags":["フィットネス","運動","手動"],"en":"Health Equipment (non-electric)"},
{"n":"高枝切りばさみ","k":["か"],"fee":200,"m":"収集／持込可","tags":["園芸","剪定","ガーデニング"],"en":"Pruning Shears"},
{"n":"米びつ","k":["か"],"fee":200,"m":"収集／持込可","tags":["米","台所","収納"],"en":"Rice Container"},
{"n":"ゴルフバッグ","k":["か"],"fee":200,"m":"収集／持込可","tags":["ゴルフ","バッグ","スポーツ"],"en":"Golf Bag"},
{"n":"ゴルフクラブ（一式）","k":["か"],"fee":400,"m":"収集／持込可","tags":["ゴルフ","クラブ","スポーツ"],"en":"Golf Clubs (set)"},
{"n":"こたつふとん","k":["か"],"fee":200,"m":"収集／持込可","tags":["炬燵","布団","暖房"],"en":"Kotatsu Futon"},
{"n":"コンポステレオ","k":["か"],"fee":400,"m":"収集／持込可","tags":["音響","ステレオ","オーディオ"],"en":"Stereo Component"},
{"n":"子供用三輪車","k":["か"],"fee":200,"m":"収集／持込可","tags":["子供","三輪車","乗物"],"en":"Children's Tricycle"},
{"n":"子供用乗物","k":["か"],"fee":200,"m":"収集／持込可","tags":["子供","乗物","おもちゃ"],"en":"Children's Ride-on Toy"},
{"n":"子供用机","k":["か"],"fee":400,"m":"収集／持込可","tags":["学習机","子供","机"],"en":"Children's Desk"},
{"n":"子供用いす","k":["か"],"fee":200,"m":"収集／持込可","tags":["子供","椅子","学習"],"en":"Children's Chair"},
{"n":"こいのぼり一式","k":["か"],"fee":200,"m":"収集／持込可","tags":["端午","行事","季節"],"en":"Carp Streamer Set"},
{"n":"サイクリングマシーン","k":["さ"],"fee":600,"m":"収集／持込可","tags":["エアロバイク","フィットネス","運動"],"en":"Exercise Bike"},
{"n":"サマーベッド","k":["さ"],"fee":200,"m":"収集／持込可","tags":["折り畳み","アウトドア","ベッド"],"en":"Summer Bed / Cot"},
{"n":"サイドボード","k":["さ"],"fee":600,"m":"収集／持込可","tags":["収納","リビング","戸棚"],"en":"Sideboard"},
{"n":"サイドテーブル","k":["さ"],"fee":200,"m":"収集／持込可","tags":["小型机","ベッドサイド","補助"],"en":"Side Table"},
{"n":"座いす","k":["さ"],"fee":200,"m":"収集／持込可","tags":["和室","椅子","座椅子"],"en":"Floor Chair (Zaisu)"},
{"n":"座卓（ちゃぶ台）","k":["さ"],"fee":400,"m":"収集／持込可","tags":["和室","机","ちゃぶ台"],"en":"Low Table (Zataku)"},
{"n":"自転車（大人用・16インチ超）","k":["さ"],"fee":600,"m":"収集／持込可","tags":["大人用","チャリ","ロードバイク"],"en":"Bicycle (adult, over 16 inch)"},
{"n":"子供用自転車（16インチ以下）","k":["さ"],"fee":400,"m":"収集／持込可","tags":["子供","チャリ","16インチ"],"en":"Children's Bicycle (16 inch or under)"},
{"n":"敷物（4畳半迄／木製除く）","k":["さ"],"fee":200,"m":"収集／持込可","tags":["カーペット","ラグ","マット"],"en":"Rug (under 4.5 tatami)"},
{"n":"敷物（4畳半超／木製除く）","k":["さ"],"fee":400,"m":"収集／持込可","tags":["カーペット","ラグ","大型"],"en":"Rug (over 4.5 tatami)"},
{"n":"シングルベッド（マット除く）","k":["さ"],"fee":800,"m":"収集／持込可","tags":["ベッド","シングル","セミダブル"],"en":"Single / Semi-double Bed (frame only)"},
{"n":"除湿機","k":["さ"],"fee":800,"m":"収集／持込可","tags":["乾燥","湿気","梅雨"],"en":"Dehumidifier"},
{"n":"照明機器","k":["さ"],"fee":200,"m":"収集／持込可","tags":["ライト","シーリング","蛍光灯"],"en":"Light Fixture"},
{"n":"ショッピングカート","k":["さ"],"fee":200,"m":"収集／持込可","tags":["買い物","カート","シルバーカー"],"en":"Shopping Cart"},
{"n":"スーツケース","k":["さ"],"fee":200,"m":"収集／持込可","tags":["旅行","鞄","キャリーケース"],"en":"Suitcase"},
{"n":"すだれ","k":["さ"],"fee":200,"m":"収集／持込可","tags":["日よけ","和","簾"],"en":"Bamboo Blind"},
{"n":"スキー板","k":["さ"],"fee":200,"m":"収集／持込可","tags":["スキー","スポーツ","冬"],"en":"Ski Board"},
{"n":"スコップ","k":["さ"],"fee":200,"m":"収集／持込可","tags":["園芸","DIY","土"],"en":"Shovel"},
{"n":"スノーボード","k":["さ"],"fee":200,"m":"収集／持込可","tags":["スノボ","スポーツ","冬"],"en":"Snowboard"},
{"n":"扇風機","k":["さ"],"fee":200,"m":"収集／持込可","tags":["ファン","夏","冷房"],"en":"Electric Fan"},
{"n":"掃除機","k":["さ"],"fee":200,"m":"収集／持込可","tags":["クリーナー","バキューム","家電"],"en":"Vacuum Cleaner"},
{"n":"スピーカー（大型1本）","k":["さ"],"fee":400,"m":"収集／持込可","tags":["音響","オーディオ","大型"],"en":"Speaker (large, 1 unit)"},
{"n":"スピーカー（小型）","k":["さ"],"fee":200,"m":"収集／持込可","tags":["音響","小型","オーディオ"],"en":"Speaker (small)"},
{"n":"ステレオセット","k":["さ"],"fee":600,"m":"収集／持込可","tags":["音響","オーディオ","セット"],"en":"Stereo Set"},
{"n":"ストーブ（電気・小型）","k":["さ"],"fee":200,"m":"収集／持込可","tags":["暖房","電気","小型"],"en":"Electric Stove (small)"},
{"n":"ストーブ（石油・反射式）","k":["さ"],"fee":400,"m":"収集／持込可","tags":["暖房","石油","反射式"],"en":"Kerosene Stove (reflector)"},
{"n":"ストーブ（石油・ファン式）","k":["さ"],"fee":600,"m":"収集／持込可","tags":["暖房","石油","ファン式"],"en":"Kerosene Fan Heater"},
{"n":"スノコ（押入れ用）","k":["さ"],"fee":200,"m":"収集／持込可","tags":["押入れ","収納","木製"],"en":"Slatted Floor Board"},
{"n":"すべり台（家庭用）","k":["さ"],"fee":400,"m":"収集／持込可","tags":["子供","遊具","家庭用"],"en":"Slide (home use)"},
{"n":"鈴虫飼育ケース","k":["さ"],"fee":200,"m":"収集／持込可","tags":["昆虫","飼育","ケース"],"en":"Insect Cage"},
{"n":"剪定枝","k":["さ"],"fee":0,"m":"収集／持込可（無料）","tags":["庭","枝","ガーデニング"],"en":"Pruned Branches (free)"},
{"n":"洗濯ハンガー（金属・大型）","k":["さ"],"fee":200,"m":"収集／持込可","tags":["物干し","ハンガー","洗濯"],"en":"Laundry Hanger (large)"},
{"n":"洗面化粧台","k":["さ"],"fee":1200,"m":"収集／持込可","tags":["洗面","化粧","水回り"],"en":"Bathroom Vanity"},
{"n":"そりっぱー（大型遊具）","k":["さ"],"fee":200,"m":"収集／持込可","tags":["子供","遊具","そり"],"en":"Sled (large toy)"},
{"n":"タンス・戸棚（3辺の和150cm未満）","k":["た"],"fee":400,"m":"収集／持込可","tags":["タンス","戸棚","小型家具"],"en":"Cabinet (sum of 3 sides under 150cm)"},
{"n":"タンス・戸棚（3辺の和150〜200cm）","k":["た"],"fee":600,"m":"収集／持込可","tags":["タンス","戸棚","中型家具"],"en":"Cabinet (sum of 3 sides 150-200cm)"},
{"n":"タンス・戸棚（3辺の和200〜250cm）","k":["た"],"fee":800,"m":"収集／持込可","tags":["タンス","戸棚","大型家具"],"en":"Cabinet (sum of 3 sides 200-250cm)"},
{"n":"タンス・戸棚（3辺の和250〜350cm）","k":["た"],"fee":1200,"m":"収集／持込可","tags":["タンス","戸棚","大型家具"],"en":"Cabinet (sum of 3 sides 250-350cm)"},
{"n":"タンス・戸棚（3辺の和350cm以上）","k":["た"],"fee":1600,"m":"収集／持込可","tags":["タンス","戸棚","超大型家具"],"en":"Cabinet (sum of 3 sides 350cm+)"},
{"n":"畳（半畳）","k":["た"],"fee":400,"m":"収集／持込可","tags":["畳","和室","半畳"],"en":"Tatami (half)"},
{"n":"畳（1畳）","k":["た"],"fee":800,"m":"収集／持込可","tags":["畳","和室","床材"],"en":"Tatami (1 mat)"},
{"n":"ダブルベッド（マット除く）","k":["た"],"fee":1600,"m":"収集／持込可","tags":["ベッド","ダブル","二段"],"en":"Double / Bunk Bed (frame only)"},
{"n":"チャイルドシート","k":["た"],"fee":200,"m":"収集／持込可","tags":["車","乳児","子供"],"en":"Child Seat"},
{"n":"チェーン","k":["た"],"fee":200,"m":"収集／持込可","tags":["金属","鎖","タイヤ"],"en":"Chain"},
{"n":"卓球台（家庭用）","k":["た"],"fee":1600,"m":"収集／持込可","tags":["スポーツ","卓球","台"],"en":"Ping Pong Table"},
{"n":"棚（小型）","k":["た"],"fee":200,"m":"収集／持込可","tags":["収納","ラック","本棚"],"en":"Shelf (small)"},
{"n":"棚（大型）","k":["た"],"fee":600,"m":"収集／持込可","tags":["収納","ラック","本棚"],"en":"Shelf (large)"},
{"n":"暖房器具（小型）","k":["た"],"fee":200,"m":"収集／持込可","tags":["暖房","ヒーター","電気"],"en":"Heater (small)"},
{"n":"釣り竿（複数本）","k":["た"],"fee":200,"m":"収集／持込可","tags":["釣り","ロッド","スポーツ"],"en":"Fishing Rod"},
{"n":"机（学習机）","k":["た"],"fee":600,"m":"収集／持込可","tags":["学習","机","勉強"],"en":"Study Desk"},
{"n":"机（事務机）","k":["た"],"fee":800,"m":"収集／持込可","tags":["オフィス","机","事務"],"en":"Office Desk"},
{"n":"ティーテーブル","k":["た"],"fee":400,"m":"収集／持込可","tags":["リビング","テーブル","小型"],"en":"Tea Table"},
{"n":"テーブル（小型）","k":["た"],"fee":400,"m":"収集／持込可","tags":["机","リビング","食卓"],"en":"Table (small)"},
{"n":"テーブル（大型）","k":["た"],"fee":600,"m":"収集／持込可","tags":["机","ダイニング","食卓"],"en":"Table (large)"},
{"n":"テレビ台（小型）","k":["た"],"fee":400,"m":"収集／持込可","tags":["AV","収納","TVボード"],"en":"TV Stand (small)"},
{"n":"テレビ台（大型）","k":["た"],"fee":600,"m":"収集／持込可","tags":["AV","収納","TVボード"],"en":"TV Stand (large)"},
{"n":"電気カーペット","k":["た"],"fee":400,"m":"収集／持込可","tags":["暖房","カーペット","電気"],"en":"Electric Carpet"},
{"n":"電気こたつセット","k":["た"],"fee":400,"m":"収集／持込可","tags":["炬燵","暖房","セット"],"en":"Electric Kotatsu Set"},
{"n":"電気スタンド","k":["た"],"fee":200,"m":"収集／持込可","tags":["照明","ライト","卓上"],"en":"Desk Lamp"},
{"n":"電気掃除機","k":["た"],"fee":200,"m":"収集／持込可","tags":["クリーナー","掃除","家電"],"en":"Electric Vacuum Cleaner"},
{"n":"電子レンジ（オーブン含む）","k":["た"],"fee":600,"m":"収集／持込可","tags":["レンジ","オーブン","調理"],"en":"Microwave Oven"},
{"n":"電子ピアノ","k":["た"],"fee":1600,"m":"収集／持込可","tags":["楽器","ピアノ","電子"],"en":"Electric Piano"},
{"n":"電動工具（大型）","k":["た"],"fee":400,"m":"収集／持込可","tags":["DIY","工具","電動"],"en":"Power Tool (large)"},
{"n":"灯油タンク（ポリ容器・大型）","k":["た"],"fee":200,"m":"収集／持込可","tags":["灯油","ポリタンク","容器"],"en":"Kerosene Tank (large)"},
{"n":"投光器","k":["た"],"fee":200,"m":"収集／持込可","tags":["照明","屋外","ライト"],"en":"Floodlight"},
{"n":"トランク（大型旅行鞄）","k":["た"],"fee":200,"m":"収集／持込可","tags":["旅行","鞄","大型"],"en":"Trunk (large)"},
{"n":"トレーニングマシン","k":["た"],"fee":1200,"m":"収集／持込可","tags":["フィットネス","運動","ジム"],"en":"Training Machine"},
{"n":"ドラム（楽器）","k":["た"],"fee":600,"m":"収集／持込可","tags":["楽器","打楽器","音楽"],"en":"Drum (musical)"},
{"n":"ドラム式洗濯機架台","k":["た"],"fee":400,"m":"収集／持込可","tags":["洗濯機","架台","ドラム"],"en":"Drum Washer Stand"},
{"n":"ドアチェーン・ドアノブ（金属類）","k":["た"],"fee":200,"m":"収集／持込可","tags":["金属","ドア","小物"],"en":"Door Chain / Knob"},
{"n":"二段ベッド（マット除く）","k":["な"],"fee":1600,"m":"収集／持込可","tags":["ベッド","2段","子供"],"en":"Bunk Bed (frame only)"},
{"n":"日本人形ケース","k":["な"],"fee":400,"m":"収集／持込可","tags":["人形","ケース","和"],"en":"Japanese Doll Case"},
{"n":"延長コード（束ねたもの）","k":["な"],"fee":200,"m":"収集／持込可","tags":["コード","電気","電源"],"en":"Extension Cord (bundled)"},
{"n":"ぬいぐるみ（特大）","k":["な"],"fee":200,"m":"収集／持込可","tags":["おもちゃ","大型","子供"],"en":"Stuffed Toy (extra large)"},
{"n":"猫タワー","k":["な"],"fee":400,"m":"収集／持込可","tags":["ペット","猫","タワー"],"en":"Cat Tower"},
{"n":"ネット（園芸・大型）","k":["な"],"fee":200,"m":"収集／持込可","tags":["園芸","ネット","ガーデニング"],"en":"Garden Net (large)"},
{"n":"パイプハンガー","k":["は"],"fee":200,"m":"収集／持込可","tags":["衣類","ハンガー","ラック"],"en":"Pipe Hanger"},
{"n":"パイプベッド","k":["は"],"fee":800,"m":"収集／持込可","tags":["ベッド","パイプ","金属"],"en":"Pipe Bed"},
{"n":"ハンガーラック","k":["は"],"fee":200,"m":"収集／持込可","tags":["衣類","ハンガー","収納"],"en":"Hanger Rack"},
{"n":"バーベキューコンロ","k":["は"],"fee":200,"m":"収集／持込可","tags":["BBQ","アウトドア","コンロ"],"en":"BBQ Grill"},
{"n":"バットケース","k":["は"],"fee":200,"m":"収集／持込可","tags":["野球","スポーツ","ケース"],"en":"Bat Case"},
{"n":"バランスボール","k":["は"],"fee":200,"m":"収集／持込可","tags":["フィットネス","運動","ボール"],"en":"Balance Ball"},
{"n":"バルブヒーター","k":["は"],"fee":400,"m":"収集／持込可","tags":["暖房","ハロゲン","電気"],"en":"Halogen Heater"},
{"n":"バンボ（ベビーチェア）","k":["は"],"fee":200,"m":"収集／持込可","tags":["乳児","椅子","ベビー"],"en":"Baby Floor Seat"},
{"n":"ピアノ用いす","k":["は"],"fee":400,"m":"収集／持込可","tags":["ピアノ","椅子","楽器"],"en":"Piano Bench"},
{"n":"ビーチパラソル","k":["は"],"fee":200,"m":"収集／持込可","tags":["パラソル","ビーチ","日よけ"],"en":"Beach Parasol"},
{"n":"ビデオデッキ","k":["は"],"fee":200,"m":"収集／持込可","tags":["AV","録画","家電"],"en":"VCR"},
{"n":"ファクシミリ（FAX）","k":["は"],"fee":200,"m":"収集／持込可","tags":["FAX","通信","事務"],"en":"Fax Machine"},
{"n":"ファンヒーター（電気）","k":["は"],"fee":400,"m":"収集／持込可","tags":["暖房","ファン","電気"],"en":"Electric Fan Heater"},
{"n":"風呂イス・風呂ふた","k":["は"],"fee":200,"m":"収集／持込可","tags":["風呂","入浴","プラ"],"en":"Bath Stool / Cover"},
{"n":"風呂釜（バランス釜）","k":["は"],"fee":1200,"m":"収集／持込可","tags":["風呂","給湯","設備"],"en":"Bath Boiler"},
{"n":"プランター（大型）","k":["は"],"fee":200,"m":"収集／持込可","tags":["園芸","鉢","ガーデニング"],"en":"Planter (large)"},
{"n":"プリンター（家庭用）","k":["は"],"fee":400,"m":"収集／持込可","tags":["事務","印刷","家電"],"en":"Printer (home)"},
{"n":"プロジェクター","k":["は"],"fee":400,"m":"収集／持込可","tags":["映像","AV","投影"],"en":"Projector"},
{"n":"フロアスタンド（照明）","k":["は"],"fee":200,"m":"収集／持込可","tags":["照明","スタンド","ライト"],"en":"Floor Lamp"},
{"n":"ふとん（1枚）","k":["は"],"fee":200,"m":"収集／持込可","tags":["寝具","掛け布団","敷布団"],"en":"Futon (1 piece)"},
{"n":"ふとん乾燥機","k":["は"],"fee":200,"m":"収集／持込可","tags":["布団","乾燥","家電"],"en":"Futon Dryer"},
{"n":"ふとん収納袋（特大）","k":["は"],"fee":200,"m":"収集／持込可","tags":["寝具","収納","袋"],"en":"Futon Storage Bag"},
{"n":"ブラインド","k":["は"],"fee":200,"m":"収集／持込可","tags":["カーテン","窓","ロール"],"en":"Blinds"},
{"n":"ブラウン管モニター（PC用・小型）","k":["は"],"fee":400,"m":"収集／持込可","tags":["PC","モニター","CRT"],"en":"CRT Monitor (small)"},
{"n":"ブランコ（家庭用）","k":["は"],"fee":600,"m":"収集／持込可","tags":["遊具","子供","庭"],"en":"Swing (home use)"},
{"n":"ベッドマット（スプリング付き）","k":["は"],"fee":800,"m":"収集／持込可","tags":["マットレス","寝具","スプリング"],"en":"Bed Mattress (with spring)"},
{"n":"ベッドマット（スプリングなし）","k":["は"],"fee":200,"m":"収集／持込可","tags":["マットレス","寝具","ノンスプリング"],"en":"Bed Mattress (without spring)"},
{"n":"ベビーカー（乳母車）","k":["は"],"fee":200,"m":"収集／持込可","tags":["乳児","赤ちゃん","乳母車"],"en":"Stroller"},
{"n":"ベビーチェア","k":["は"],"fee":200,"m":"収集／持込可","tags":["乳児","椅子","ハイチェア"],"en":"Baby Chair"},
{"n":"ベビーバス","k":["は"],"fee":200,"m":"収集／持込可","tags":["乳児","お風呂","赤ちゃん"],"en":"Baby Bath"},
{"n":"ベビーベッド","k":["は"],"fee":600,"m":"収集／持込可","tags":["乳児","ベッド","赤ちゃん"],"en":"Baby Bed"},
{"n":"ベビーサークル","k":["は"],"fee":400,"m":"収集／持込可","tags":["乳児","柵","赤ちゃん"],"en":"Baby Playpen"},
{"n":"ベンチ（屋外用）","k":["は"],"fee":400,"m":"収集／持込可","tags":["屋外","椅子","庭"],"en":"Outdoor Bench"},
{"n":"ペットゲージ（小型）","k":["は"],"fee":200,"m":"収集／持込可","tags":["ペット","犬","猫"],"en":"Pet Cage (small)"},
{"n":"ペットゲージ（大型）","k":["は"],"fee":400,"m":"収集／持込可","tags":["ペット","犬","大型"],"en":"Pet Cage (large)"},
{"n":"ペットキャリーバッグ","k":["は"],"fee":200,"m":"収集／持込可","tags":["ペット","運搬","キャリー"],"en":"Pet Carrier"},
{"n":"ホットカーペット","k":["は"],"fee":400,"m":"収集／持込可","tags":["暖房","カーペット","電気"],"en":"Heated Carpet"},
{"n":"ホットプレート","k":["は"],"fee":200,"m":"収集／持込可","tags":["調理","卓上","電気"],"en":"Hot Plate"},
{"n":"ホースリール","k":["は"],"fee":200,"m":"収集／持込可","tags":["園芸","水まき","ホース"],"en":"Hose Reel"},
{"n":"ボーリングのボール","k":["は"],"fee":200,"m":"収集／持込可","tags":["ボーリング","スポーツ","ボール"],"en":"Bowling Ball"},
{"n":"本棚（高さ90cm以下）","k":["は"],"fee":200,"m":"収集／持込可","tags":["収納","本","ラック"],"en":"Bookshelf (under 90cm)"},
{"n":"本棚（高さ90cm超）","k":["は"],"fee":400,"m":"収集／持込可","tags":["収納","本","大型"],"en":"Bookshelf (over 90cm)"},
{"n":"マッサージチェア","k":["ま"],"fee":600,"m":"収集／持込可","tags":["健康","椅子","リラックス"],"en":"Massage Chair"},
{"n":"マットレス（1枚）","k":["ま"],"fee":200,"m":"収集／持込可","tags":["寝具","敷布団","マット"],"en":"Mattress (1 piece)"},
{"n":"麻雀卓（家庭用・全自動以外）","k":["ま"],"fee":600,"m":"収集／持込可","tags":["麻雀","卓","ゲーム"],"en":"Mahjong Table (manual)"},
{"n":"麻雀卓（全自動式）","k":["ま"],"fee":1600,"m":"収集／持込可","tags":["麻雀","全自動","卓"],"en":"Mahjong Table (automatic)"},
{"n":"マット（ヨガマット・トレーニング用）","k":["ま"],"fee":200,"m":"収集／持込可","tags":["ヨガ","フィットネス","マット"],"en":"Yoga / Training Mat"},
{"n":"ミシン（卓上式）","k":["ま"],"fee":400,"m":"収集／持込可","tags":["手芸","裁縫","卓上"],"en":"Sewing Machine (tabletop)"},
{"n":"ミシン（卓上式以外）","k":["ま"],"fee":1200,"m":"収集／持込可","tags":["手芸","裁縫","業務用"],"en":"Sewing Machine (non-tabletop)"},
{"n":"ミラー（姿見・大型）","k":["ま"],"fee":400,"m":"収集／持込可","tags":["鏡","姿見","ミラー"],"en":"Full-Length Mirror"},
{"n":"水切りラック（大型）","k":["ま"],"fee":200,"m":"収集／持込可","tags":["台所","水切り","収納"],"en":"Dish Rack (large)"},
{"n":"虫取り網","k":["ま"],"fee":200,"m":"収集／持込可","tags":["昆虫","網","子供"],"en":"Insect Net"},
{"n":"モップ","k":["ま"],"fee":200,"m":"収集／持込可","tags":["掃除","モップ","清掃"],"en":"Mop"},
{"n":"物干し竿","k":["ま"],"fee":200,"m":"収集／持込可","tags":["洗濯","物干し","竿"],"en":"Laundry Pole"},
{"n":"物干しスタンド（金属）","k":["ま"],"fee":400,"m":"収集／持込可","tags":["洗濯","物干し","スタンド"],"en":"Laundry Drying Stand"},
{"n":"湯沸器","k":["や"],"fee":400,"m":"収集／持込可","tags":["給湯","ボイラー","風呂"],"en":"Water Heater"},
{"n":"湯たんぽ（金属製）","k":["や"],"fee":200,"m":"収集／持込可","tags":["暖房","金属","冬"],"en":"Hot Water Bottle (metal)"},
{"n":"洋服掛け（木製）","k":["や"],"fee":200,"m":"収集／持込可","tags":["衣類","ハンガー","木製"],"en":"Clothes Rack (wooden)"},
{"n":"ヨガマット（厚手）","k":["や"],"fee":200,"m":"収集／持込可","tags":["ヨガ","運動","マット"],"en":"Yoga Mat (thick)"},
{"n":"落ち葉・刈草","k":["あ"],"fee":0,"m":"収集／持込可（無料）","tags":["落葉","草","ガーデニング"],"en":"Fallen Leaves / Cut Grass (free)"},
{"n":"ラジカセ","k":["ら"],"fee":200,"m":"収集／持込可","tags":["音響","ラジオ","カセット"],"en":"Radio Cassette Player"},
{"n":"ラック（金属・スチール）","k":["ら"],"fee":400,"m":"収集／持込可","tags":["収納","金属","ラック"],"en":"Steel Rack"},
{"n":"ランニングマシン","k":["ら"],"fee":1600,"m":"収集／持込可","tags":["フィットネス","運動","ジム"],"en":"Running Machine"},
{"n":"リクライニングチェア","k":["ら"],"fee":600,"m":"収集／持込可","tags":["椅子","リクライニング","リラックス"],"en":"Reclining Chair"},
{"n":"リコーダー（大型・楽器）","k":["ら"],"fee":200,"m":"収集／持込可","tags":["楽器","木管","音楽"],"en":"Recorder (large musical)"},
{"n":"レコードプレーヤー","k":["ら"],"fee":400,"m":"収集／持込可","tags":["音響","レコード","オーディオ"],"en":"Record Player"},
{"n":"冷風扇","k":["ら"],"fee":400,"m":"収集／持込可","tags":["冷房","扇風機","ファン"],"en":"Cool Air Fan"},
{"n":"レンジ台（キッチン）","k":["ら"],"fee":400,"m":"収集／持込可","tags":["キッチン","収納","レンジ"],"en":"Microwave Stand"},
{"n":"ロッキングチェア","k":["ら"],"fee":400,"m":"収集／持込可","tags":["椅子","木製","リラックス"],"en":"Rocking Chair"},
{"n":"ロフトベッド","k":["ら"],"fee":1600,"m":"収集／持込可","tags":["ベッド","ハイ","パイプ"],"en":"Loft Bed"},
{"n":"ロールカーテン","k":["ら"],"fee":200,"m":"収集／持込可","tags":["カーテン","ロール","窓"],"en":"Roll Curtain"},
{"n":"ワゴン","k":["わ"],"fee":200,"m":"収集／持込可","tags":["キッチンワゴン","収納","キャスター"],"en":"Wagon"},
{"n":"ワインセラー（小型）","k":["わ"],"fee":600,"m":"収集／持込可","tags":["ワイン","保冷","家電"],"en":"Wine Cellar (small)"},
{"n":"輪投げセット","k":["わ"],"fee":200,"m":"収集／持込可","tags":["遊具","子供","ゲーム"],"en":"Ring Toss Set"},
{"n":"建具（網戸・障子・ふすま）","k":["た"],"fee":200,"m":"収集／持込可","tags":["襖","障子","網戸"],"en":"Door / Shoji / Fusuma"},
{"n":"その他（3辺150cm未満／重量5〜10kg）","k":["さ"],"fee":200,"m":"収集／持込可","tags":["サイズ別","汎用","重量別"],"en":"Other (under 150cm / 5-10kg)"},
{"n":"その他（3辺150〜200cm／重量10〜15kg）","k":["さ"],"fee":400,"m":"収集／持込可","tags":["サイズ別","汎用","重量別"],"en":"Other (150-200cm / 10-15kg)"},
{"n":"その他（3辺200〜300cm／重量15〜20kg）","k":["さ"],"fee":600,"m":"収集／持込可","tags":["サイズ別","汎用","重量別"],"en":"Other (200-300cm / 15-20kg)"},
{"n":"その他（3辺300〜450cm／重量20〜30kg）","k":["さ"],"fee":800,"m":"収集／持込可","tags":["サイズ別","汎用","重量別"],"en":"Other (300-450cm / 20-30kg)"},
{"n":"その他（3辺450〜600cm／重量30〜40kg）","k":["さ"],"fee":1200,"m":"収集／持込可","tags":["サイズ別","汎用","重量別"],"en":"Other (450-600cm / 30-40kg)"},
{"n":"その他（3辺600〜850cm／重量40〜60kg）","k":["さ"],"fee":1600,"m":"収集／持込可","tags":["サイズ別","汎用","重量別"],"en":"Other (600-850cm / 40-60kg)"},
{"n":"その他（3辺850cm以上／重量60kg以上）","k":["さ"],"fee":2400,"m":"収集／持込可","tags":["サイズ別","汎用","超大型"],"en":"Other (850cm+ / 60kg+)"}
],"itemSet":"tama_2026"}
